{
  "bowl": 0,
  "tomato": 1,
  "greens": 2,
  "food_bag": 3,
  "notebook": 4,
  "pear": 5,
  "lime": 6,
  "soda_can": 7,
  "ball": 8,
  "dry_battery": 9,
  "toothpaste": 10,
  "food_jar": 11,
  "potato": 12,
  "sponge": 13,
  "kleenex": 14,
  "food_box": 15,
  "food_can": 16,
  "glue_stick": 17,
  "marker": 18,
  "garlic": 19,
  "bell_pepper": 20,
  "coffee_mug": 21,
  "stapler": 22,
  "cell_phone": 23,
  "lemon": 24,
  "orange": 25,
  "food_cup": 26,
  "water_bottle": 27,
  "cereal_box": 28,
  "pliers": 29,
  "instant_noodles": 30,
  "flashlight": 31,
  "hand_towel": 32,
  "onion": 33,
  "camera": 34,
  "banana": 35,
  "plate": 36,
  "peach": 37,
  "comb": 38,
  "cap": 39,
  "shampoo": 40,
  "scissors": 41,
  "pitcher": 42,
  "toothbrush": 43,
  "mushroom": 44,
  "rubber_eraser": 45,
  "keyboard": 46,
  "binder": 47,
  "calculator": 48,
  "lightbulb": 49,
  "apple": 50
}